assets/rubin-technote/styles/SourceSans3VF-Italic.ttf.woff2
assets/rubin-technote/styles/SourceSans3VF-Upright.ttf.woff2
assets/rubin-technote/styles/_hacks.scss
assets/rubin-technote/styles/_properties.scss
assets/rubin-technote/styles/rubin-technote.scss
assets/rubin-technote/styles/components/_article-header.scss
assets/rubin-technote/styles/components/_authors.scss
assets/rubin-technote/styles/components/_global-breadcrumbs.scss
assets/rubin-technote/styles/components/_index.scss
assets/rubin-technote/styles/components/_sidebar-section.scss
assets/rubin-technote/styles/components/_version-info.scss
documenteer/__init__.py
documenteer/_packagemetadata.py
documenteer/_requestsutils.py
documenteer/_utils.py
documenteer/cli.py
documenteer/py.typed
documenteer/version.py
documenteer/assets/.gitignore
documenteer/assets/731c8feefe13e72a8691.woff2
documenteer/assets/b8bc3440ba2145e132f5.woff2
documenteer/assets/favicon.ico
documenteer/assets/rubin-favicon-transparent-32px.png
documenteer/assets/rubin-favicon.svg
documenteer/assets/rubin-pydata-theme.css
documenteer/assets/rubin-technote.css
documenteer/assets/rubin-technote.css.map
documenteer/assets/rubin-titlebar-imagotype-dark.svg
documenteer/assets/rubin-titlebar-imagotype-light.svg
documenteer/assets/rsd-assets/rubin-imagotype-color-on-black-crop.svg
documenteer/assets/rsd-assets/rubin-imagotype-color-on-white-crop.svg
documenteer/assets/scripts/rubin-technote.js
documenteer/assets/scripts/rubin-technote.js.map
documenteer/conf/__init__.py
documenteer/conf/_toml.py
documenteer/conf/_utils.py
documenteer/conf/guide.py
documenteer/conf/technote.py
documenteer/ext/__init__.py
documenteer/ext/bibtex.py
documenteer/ext/githubbibcache.py
documenteer/ext/jira.py
documenteer/ext/lsstdocushare.py
documenteer/ext/mockcoderefs.py
documenteer/ext/openapi.py
documenteer/ext/remotecodeblock.py
documenteer/ext/robots.py
documenteer/ext/redoc/__init__.py
documenteer/ext/redoc/_redoc.py
documenteer-2.3.0.dist-info/licenses/LICENSE
documenteer-2.3.0.dist-info/licenses/licenses/README.md
documenteer-2.3.0.dist-info/licenses/licenses/astropy-helpers.txt
documenteer-2.3.0.dist-info/licenses/licenses/sphinx-issue.txt
documenteer-2.3.0.dist-info/licenses/licenses/sphinx.txt
documenteer-2.3.0.dist-info/licenses/licenses/sphinxcontrib-redoc.txt
documenteer-2.3.0.dist-info/METADATA
documenteer-2.3.0.dist-info/WHEEL
documenteer-2.3.0.dist-info/entry_points.txt
documenteer-2.3.0.dist-info/top_level.txt
documenteer-2.3.0.dist-info/RECORD
